MANIFEST.in
README.rst
flask_beanstalk.py
requirements.txt
setup.py
Flask_Beanstalk.egg-info/PKG-INFO
Flask_Beanstalk.egg-info/SOURCES.txt
Flask_Beanstalk.egg-info/dependency_links.txt
Flask_Beanstalk.egg-info/not-zip-safe
Flask_Beanstalk.egg-info/pbr.json
Flask_Beanstalk.egg-info/requires.txt
Flask_Beanstalk.egg-info/top_level.txt