Metadata-Version: 1.0
Name: Flask-Beanstalk
Version: 0.0.3
Summary: Utilities for using Beanstalk with Flask
Home-page: https://github.com/marksteve/flask-beanstalk
Author: Mark Steve Samson
Author-email: hello@marksteve.com
License: MIT
Platform: any
